myiq/__init__.py
myiq/core/__init__.py
myiq/core/candle_fetcher.py
myiq/core/client.py
myiq/core/connection.py
myiq/core/constants.py
myiq/core/dispatcher.py
myiq/core/explorer.py
myiq/core/reconnect.py
myiq/core/utils.py
myiq/http/__init__.py
myiq/http/auth.py
myiq/models/__init__.py
myiq/models/base.py
myiq-0.1.3.dist-info/licenses/LICENSE
myiq-0.1.3.dist-info/METADATA
myiq-0.1.3.dist-info/WHEEL
myiq-0.1.3.dist-info/top_level.txt
myiq-0.1.3.dist-info/RECORD
