Metadata-Version: 2.4
Name: myiq
Version: 0.1.3
Summary: A modern, asynchronous Python library for IQ Option API
Author-email: IzioGanasi <izio.ganasi@gmail.com>
Project-URL: Homepage, https://github.com/IzioGanasi/biblioteca_myiq
Project-URL: Bug Tracker, https://github.com/IzioGanasi/biblioteca_myiq/issues
Classifier: Programming Language :: Python :: 3
Classifier: License :: OSI Approved :: MIT License
Classifier: Operating System :: OS Independent
Classifier: Intended Audience :: Developers
Classifier: Topic :: Software Development :: Libraries :: Python Modules
Requires-Python: >=3.10
License-File: LICENSE
Requires-Dist: websockets>=11.0
Requires-Dist: httpx>=0.24.0
Requires-Dist: pydantic>=2.0.0
Requires-Dist: structlog>=23.1.0
Dynamic: license-file
